countryinfo/__init__.py
countryinfo/negara.py
infokannegara-0.0.1.dist-info/LICENCE.txt
infokannegara-0.0.1.dist-info/METADATA
infokannegara-0.0.1.dist-info/WHEEL
infokannegara-0.0.1.dist-info/top_level.txt
infokannegara-0.0.1.dist-info/RECORD
