Metadata-Version: 2.1
Name: infokannegara
Version: 0.0.1
Summary: Python library leveraging REST Countries API to fetch and display country-specific data such as capitals, populations, currencies, and languages.
Home-page: https://github.com/codewithwan/infokannegara
Author: apaya
Author-email: <heyowassap@gmail.com>
License: MIT
Keywords: info,negara
Classifier: Development Status :: 1 - Planning
License-File: LICENCE.txt
